pyzas/__init__.py
pyzas/pyzas.cpython-313t-x86_64-linux-gnu.so
pyzas-1.0.1.dist-info/LICENSE
pyzas-1.0.1.dist-info/METADATA
pyzas-1.0.1.dist-info/WHEEL
pyzas-1.0.1.dist-info/RECORD
