Metadata-Version: 2.1
Name: pyzas
Version: 1.0.1
Summary: PyZas!: A Python library for atomic integer operations
Home-page: https://github.com/citiususc/pyzas
License: LGPL-3.0-only
Keywords: HPC,OMP,OpenMP,Multi-language,Programming models
Author: Cesar Pomar
Author-email: cesaralfredo.pineiro@usc.es
Requires-Python: >=3.13,<4.0
Classifier: License :: OSI Approved :: GNU Lesser General Public License v3 (LGPLv3)
Classifier: Programming Language :: Python :: 3
Classifier: Topic :: Software Development
Classifier: Topic :: Utilities
Project-URL: Repository, https://github.com/citiususc/pyzas
